langchain_altero/__init__.py
langchain_altero/callbacks.py
langchain_altero/indonesia.py
langchain_altero/logging.py
langchain_altero/messages.py
langchain_altero/models.py
langchain_altero/prompts.py
langchain_altero/community/__init__.py
langchain_altero/community/kiwi_tokenizer.py
langchain_altero/community/pinecone.py
langchain_altero/document_loaders/__init__.py
langchain_altero/document_loaders/hwp.py
langchain_altero/document_loaders/pdf.py
langchain_altero/retrievers/__init__.py
langchain_altero/retrievers/kiwi_bm25.py
langchain_altero/retrievers/konlpy_bm25.py
langchain_altero-0.0.4.dist-info/LICENSE
langchain_altero-0.0.4.dist-info/METADATA
langchain_altero-0.0.4.dist-info/WHEEL
langchain_altero-0.0.4.dist-info/top_level.txt
langchain_altero-0.0.4.dist-info/RECORD
