Metadata-Version: 2.1
Name: langchain-altero
Version: 0.0.4
Summary: Streamline your AI workflows with langChain-altero, the essential toolkit for seamless LangChain integration.
Home-page: https://github.com/cakeplabs/langchain-altero
Author: Dicky Umardhani
Author-email: dicky@alterolab.com
Keywords: langchain,altero
Classifier: Programming Language :: Python :: 3
Requires-Python: >=3.10
License-File: LICENSE
Requires-Dist: langchain
Requires-Dist: kiwipiepy
Requires-Dist: konlpy
Requires-Dist: rank-bm25
Requires-Dist: pinecone-client[grpc]
Requires-Dist: pinecone-text
Requires-Dist: olefile
Requires-Dist: pdf2image
